{
    "relationships": [
        {
            "relationshipId": 1,
            "relationshipName": "reviews",
            "otherEntityName": "user",
            "relationshipType": "many-to-one",
            "otherEntityField": "login"
        },
        {
            "relationshipId": 2,
            "relationshipName": "products",
            "otherEntityName": "products",
            "relationshipType": "many-to-one",
            "otherEntityField": "name"
        }
    ],
    "fields": [
        {
            "fieldId": 1,
            "fieldName": "rating",
            "fieldType": "BigDecimal"
        },
        {
            "fieldId": 2,
            "fieldName": "comments",
            "fieldType": "String"
        },
        {
            "fieldId": 3,
            "fieldName": "isFavourite",
            "fieldType": "Boolean"
        },
        {
            "fieldId": 4,
            "fieldName": "createdAt",
            "fieldType": "ZonedDateTime"
        },
        {
            "fieldId": 5,
            "fieldName": "updatedAt",
            "fieldType": "ZonedDateTime"
        }
    ],
    "changelogDate": "20160319180341",
    "dto": "mapstruct",
    "pagination": "pagination"
}
